{
  "id": "mix",
  "name": "Mix",
  "canonical_url": "https://mix.com",
  "engine_ref": "base_http_status",
  "classification": {
    "primary": "social",
    "identity_type": "virtual_social",
    "geo_region": "global",
    "user_scale": 999996819,
    "tags": [
      "links",
      "sharing"
    ]
  },
  "rankings": {
    "alexa": 3181
  },
  "check": {
    "probe_url": "https://mix.com/{username}",
    "known_accounts": [
      "adam"
    ],
    "known_unclaimed": [
      "noonewouldeverusethis7"
    ],
    "headers": {}
  },
  "nsfw": false,
  "deprecated": false,
  "source": "maigret_migration",
  "last_updated": "2026-05-05T03:44:11.126861+00:00"
}