{
  "id": "mywishboard_com",
  "name": "mywishboard.com",
  "canonical_url": "https://mywishboard.com",
  "engine_ref": "base_http_message",
  "classification": {
    "primary": "social",
    "identity_type": "virtual_social",
    "geo_region": "global",
    "user_scale": 999664919,
    "tags": [
      "shopping"
    ]
  },
  "rankings": {
    "alexa": 335081
  },
  "check": {
    "probe_url": "https://mywishboard.com/@{username}",
    "known_accounts": [
      "alex"
    ],
    "known_unclaimed": [
      "noonewouldeverusethis7"
    ],
    "headers": {},
    "presence_strs": [
      "profile-header",
      " profile-header__col"
    ],
    "absence_strs": [
      "This page could not be found"
    ]
  },
  "nsfw": false,
  "deprecated": false,
  "source": "maigret_migration",
  "last_updated": "2026-05-05T03:44:12.131428+00:00"
}