{
  "id": "wikidot",
  "name": "Wikidot",
  "canonical_url": "http://www.wikidot.com/",
  "engine_ref": "base_http_message",
  "classification": {
    "primary": "social",
    "identity_type": "virtual_social",
    "geo_region": "global",
    "user_scale": 999998817,
    "tags": [
      "wiki"
    ]
  },
  "rankings": {
    "alexa": 1183
  },
  "check": {
    "probe_url": "http://www.wikidot.com/user:info/{username}",
    "known_accounts": [
      "blue"
    ],
    "known_unclaimed": [
      "noonewouldeverusethis7"
    ],
    "headers": {},
    "presence_strs": [
      "Wikidot user since"
    ],
    "absence_strs": [
      "User does not exist."
    ]
  },
  "nsfw": false,
  "deprecated": false,
  "source": "maigret_migration",
  "last_updated": "2026-05-05T03:44:10.822460+00:00"
}